nlp4ss/__cli__.py
nlp4ss/__init__.py
nlp4ss/_version.py
nlp4ss/conf/about/nlp4ss.yaml
nlp4ss/py.typed
nlp4ss-0.9.0.dist-info/LICENSE
nlp4ss-0.9.0.dist-info/METADATA
nlp4ss-0.9.0.dist-info/WHEEL
nlp4ss-0.9.0.dist-info/entry_points.txt
nlp4ss-0.9.0.dist-info/RECORD
