Metadata-Version: 2.1
Name: nlp4ss
Version: 0.9.0
Summary: A course on applying natural language processing (NLP) techniques for social science research.
Home-page: https://nlp4ss.jeju.ai
License: CC-BY-4.0
Author: Young Joon Lee
Author-email: entelecheia@hotmail.com
Requires-Python: >=3.9,<3.13
Classifier: License :: Other/Proprietary License
Classifier: Programming Language :: Python :: 3
Classifier: Programming Language :: Python :: 3.9
Classifier: Programming Language :: Python :: 3.10
Classifier: Programming Language :: Python :: 3.11
Classifier: Programming Language :: Python :: 3.12
Requires-Dist: click (>=8.1.3,<9.0.0)
Requires-Dist: gensim (>=4.3.3,<5.0.0)
Requires-Dist: hyfi (>=1.36.4,<2.0.0)
Requires-Dist: nltk (<=3.9.1)
Requires-Dist: openai (>=1.35.14,<2.0.0)
Requires-Dist: pyldavis (>=3.4.1,<4.0.0)
Requires-Dist: pyyaml (>=6.0.1,<7.0.0)
Requires-Dist: scikit-learn (>=1.5.1,<2.0.0)
Requires-Dist: scipy (>=1.7.0,<1.14.0)
Requires-Dist: seaborn (>=0.13.2,<0.14.0)
Requires-Dist: sentence-transformers (>=3.0.1,<4.0.0)
Requires-Dist: spacy (>=3.7.5,<4.0.0)
Requires-Dist: textblob (>=0.18.0.post0,<0.19.0)
Requires-Dist: torch (==2.3.1)
Requires-Dist: tqdm (>=4.66.5,<5.0.0)
Requires-Dist: transformers (==4.42.4)
Requires-Dist: wordcloud (>=1.9.3,<2.0.0)
Project-URL: Repository, https://github.com/entelecheia/nlp4ss
